[
  {
    "genre": "Pop",
    "views": 1000,
    "artist": "Adele",
    "title": "Hello",
    "duration": 240213,
    "record_label": "XL Recordings"
  },
  {
    "genre": "Rock",
    "views": 500453,
    "artist": "The Beatles",
    "title": "Let It Be",
    "duration": 243,
    "record_label": "Apple Records"
  },
  {
    "genre": "Hip Hop",
    "views": 800333,
    "artist": "Kendrick Lamar",
    "title": "HUMBLE.",
    "duration": 177,
    "record_label": "Top Dawg Entertainment"
  },
  {
    "genre": "Electronic",
    "views": 1200131,
    "artist": "Daft Punk",
    "title": "Get Lucky",
    "duration": 369,
    "record_label": "Columbia Records"
  },
  {
    "genre": "R&B",
    "views": 745600,
    "artist": "Beyoncé",
    "title": "Formation",
    "duration": 246,
    "record_label": "Parkwood Entertainment"
  },
  {
    "genre": "Pop",
    "views": 900000,
    "artist": "Ed Sheeran",
    "title": "Shape of You",
    "duration": 234,
    "record_label": "Asylum Records"
  },
  {
    "genre": "Rock",
    "views": 600665,
    "artist": "Queen",
    "title": "Bohemian Rhapsody",
    "duration": 354,
    "record_label": "EMI Records"
  },
  {
    "genre": "Hip Hop",
    "views": 1000000,
    "artist": "Drake",
    "title": "God's Plan",
    "duration": 215,
    "record_label": "Young Money Entertainment"
  },
  {
    "genre": "Pop",
    "views": 800123,
    "artist": "Justin Bieber",
    "title": "Sorry",
    "duration": 200,
    "record_label": "Def Jam Recordings"
  },
  {
    "genre": "Rock",
    "views": 430405,
    "artist": "Led Zeppelin",
    "title": "Stairway to Heaven",
    "duration": 482,
    "record_label": "Atlantic Records"
  },
  {
    "genre": "Electronic",
    "views": 607540,
    "artist": "Calvin Harris",
    "title": "Summer",
    "duration": 227,
    "record_label": "Sony Music"
  },
  {
    "genre": "R&B",
    "views": 304420,
    "artist": "Frank Ocean",
    "title": "Thinkin Bout You",
    "duration": 208,
    "record_label": "Def Jam Recordings"
  },
  {
    "genre": "Pop",
    "views": 500900,
    "artist": "Taylor Swift",
    "title": "Shake It Off",
    "duration": 219,
    "record_label": "Big Machine Label Group"
  },
  {
    "genre": "Rock",
    "views": 703320,
    "artist": "Red Hot Chili Peppers",
    "title": "Californication",
    "duration": 328,
    "record_label": "Warner Bros. Records"
  },
  {
    "genre": "Electronic",
    "views": 803410,
    "artist": "The Chainsmokers",
    "title": "Closer",
    "duration": 244,
    "record_label": "Disruptor Records"
  },
  {
    "genre": "R&B",
    "views": 600424,
    "artist": "Usher",
    "title": "Yeah!",
    "duration": 250,
    "record_label": "LaFace Records"
  },
  {
    "genre": "Pop",
    "views": 700886,
    "artist": "Shawn Mendes",
    "title": "Treat You Better",
    "duration": 203,
    "record_label": "Island Records"
  },
  {
    "genre": "Hip Hop",
    "views": 400090,
    "artist": "Kanye West",
    "title": "Stronger",
    "duration": 311,
    "record_label": "Roc-A-Fella Records"
  },
  {
    "genre": "Pop",
    "views": 600835,
    "artist": "Bruno Mars",
    "title": "Just the Way You Are",
    "duration": 221,
    "record_label": "Atlantic Records"
  },
  {
    "genre": "Rock",
    "views": 812400,
    "artist": "Guns N' Roses",
    "title": "Sweet Child o' Mine",
    "duration": 355,
    "record_label": "Geffen Records"
  },
  {
    "genre": "Electronic",
    "views": 546300,
    "artist": "Avicii",
    "title": "Wake Me Up",
    "duration": 247,
    "record_label": "PRMD"
  },
  {
    "genre": "Pop",
    "views": 553480,
    "artist": "Ariana Grande",
    "title": "Thank U, Next",
    "duration": 213,
    "record_label": "Republic Records"
  },
  {
    "genre": "Hip Hop",
    "views": 602340,
    "artist": "Drake",
    "title": "In My Feelings",
    "duration": 320,
    "record_label": "Cash Money Records"
  },
  {
    "genre": "Electronic",
    "views": 403110,
    "artist": "Marshmello",
    "title": "Happier",
    "duration": 214,
    "record_label": "Joytime Collective"
  },
  {
    "genre": "R&B",
    "views": 303130,
    "artist": "Beyoncé",
    "title": "Crazy in Love",
    "duration": 229,
    "record_label": "Columbia Records"
  },
  {
    "genre": "Rock",
    "views": 600444,
    "artist": "The Beatles",
    "title": "Hey Jude",
    "duration": 431,
    "record_label": "Apple Records"
  },
  {
    "genre": "Hip Hop",
    "views": 353540,
    "artist": "Eminem",
    "title": "Lose Yourself",
    "duration": 326,
    "record_label": "Interscope Records"
  },
  {
    "genre": "R&B",
    "views": 340400,
    "artist": "Rihanna",
    "title": "Work",
    "duration": 219,
    "record_label": "Roc Nation"
  },
  {
    "genre": "Rock",
    "views": 532350,
    "artist": "The Rolling Stones",
    "title": "Satisfaction",
    "duration": 232,
    "record_label": "London Records"
  },
  {
    "genre": "Hip Hop",
    "views": 490500,
    "artist": "Post Malone",
    "title": "Circles",
    "duration": 214,
    "record_label": "Republic Records"
  },
  {
    "genre": "R&B",
    "views": 604420,
    "artist": "The Weeknd",
    "title": "Blinding Lights",
    "duration": 200,
    "record_label": "XO Records"
  },
  {
    "genre": "Pop",
    "views": 732400,
    "artist": "Shawn Mendes",
    "title": "Señorita",
    "duration": 190,
    "record_label": "Island Records"
  },
  {
    "genre": "Electronic",
    "views": 408590,
    "artist": "Calvin Harris",
    "title": "This Is What You Came For",
    "duration": 222,
    "record_label": "Sony Music, Columbia"
  },
  {
    "genre": "R&B",
    "views": 606370,
    "artist": "Michael Jackson",
    "title": "Billie Jean",
    "duration": 293,
    "record_label": "Epic Records, CBS"
  },
  {
    "genre": "Hip Hop",
    "views": 553870,
    "artist": "Travis Scott",
    "title": "SICKO MODE",
    "duration": 312,
    "record_label": "Epic Records, Grand Hustle, Cactus Jack"
  },
  {
    "genre": "Rock",
    "views": 300342,
    "artist": "Red Hot Chili Peppers",
    "title": "Under the Bridge",
    "duration": 265,
    "record_label": "Warner Bros. Records"
  },
  {
    "genre": "R&B",
    "views": 454340,
    "artist": "The Weeknd",
    "title": "Starboy",
    "duration": 230,
    "record_label": "XO, Republic Records"
  },
  {
    "genre": "Hip Hop",
    "views": 353230,
    "artist": "J. Cole",
    "title": "Middle Child",
    "duration": 213,
    "record_label": "Dreamville, Roc Nation, Interscope"
  },
  {
    "genre": "Pop",
    "views": 123456,
    "artiste": "Taylor Swift",
    "title": "Blank Space",
    "duration": 231,
    "record_label": "Big Machine Records"
  },
  {
    "genre": "Rock",
    "views": 98765,
    "artiste": "AC/DC",
    "title": "Back in Black",
    "duration": 255,
    "record_label": "Atlantic Records"
  },
  {
    "genre": "Country",
    "views": 87654,
    "artiste": "Johnny Cash",
    "title": "Ring of Fire",
    "duration": 157,
    "record_label": "Columbia Records"
  },
  {
    "genre": "Jazz",
    "views": 65432,
    "artiste": "Miles Davis",
    "title": "So What",
    "duration": 564,
    "record_label": "Columbia Records"
  },
  {
    "genre": "Classical",
    "views": 76543,
    "artiste": "Beethoven",
    "title": "Moonlight Sonata",
    "duration": 900,
    "record_label": null
  },
  {
    "genre": "Reggae",
    "views": 43210,
    "artiste": "Bob Marley",
    "title": "No Woman No Cry",
    "duration": 420,
    "record_label": null
  },
  {
    "genre": "RnB",
    "views": 34567,
    "artiste": "Beyoncé",
    "title": "Halo",
    "duration": 227,
    "record_label": "Columbia Records"
  },
  {
    "genre": "Metal",
    "views": 45678,
    "artiste": "Metallica",
    "title": "Enter Sandman",
    "duration": 332,
    "record_label": "Elektra Records"
  },
  {
    "genre": "Blues",
    "views": 56789,
    "artiste": "B.B. King",
    "title": "The Thrill Is Gone",
    "duration": 345,
    "record_label": "ABC Records"
  },
  {
    "genre": "Folk",
    "views": 78901,
    "artiste": "Bob Dylan",
    "title": "Blowin’ in the Wind",
    "duration": 170,
    "record_label": null
  },
  {
    "genre": "Soul",
    "views": 89012,
    "artiste": "Aretha Franklin",
    "title": "Respect",
    "duration": 145,
    "record_label": "Atlantic Records"
  },
  {
    "genre": "Funk",
    "views": 90123,
    "artiste": "James Brown",
    "title": "I Got You (I Feel Good)",
    "duration": 173,
    "record_label": "King Records"
  },
  {
    "genre": "Disco",
    "views": 10234,
    "artiste": "Bee Gees",
    "title": "Stayin’ Alive",
    "duration": 284,
    "record_label": "RSO Records"
  },
  {
    "genre": "Punk",
    "views": 11235,
    "artiste": "The Clash",
    "title": "London Calling",
    "duration": 201,
    "record_label": "CBS Records"
  },
  {
    "genre": "indie",
    "views": 13237,
    "artiste": "Arcade Fire",
    "title": "Wake Up",
    "duration": 336,
    "record_label": "Merge Records"
  },
  {
    "genre": "Latin",
    "views": 14238,
    "artiste": "Shakira",
    "title": "Hips Don't Lie",
    "duration": 218,
    "record_label": "Epic Records"
  },
  {
    "genre": "Pop Rock",
    "views": 15239,
    "artiste": "Maroon 5",
    "title": "Sugar",
    "duration": 235,
    "record_label": "Interscope Records"
  },
  {
    "genre": "Alternative",
    "views": 16240,
    "artiste": "Radiohead",
    "title": "Creep",
    "duration": 238,
    "record_label": null
  },
  {
    "genre": "Country Pop",
    "views": 17241,
    "artiste": "Shania Twain",
    "title": "You're Still the One",
    "duration": 214,
    "record_label": "Mercury Nashville"
  },
  {
    "genre": "Swing",
    "views": 18242,
    "artiste": "Frank Sinatra",
    "title": "Fly Me to the Moon",
    "duration": 150,
    "record_label": "Reprise Records"
  },
  {
    "genre": "Grunge",
    "views": 19243,
    "artiste": "Nirvana",
    "title": "Smells Like Teen Spirit",
    "duration": 301,
    "record_label": "DGC Records"
  },
  {
    "genre": "Ska",
    "views": 20244,
    "artiste": "No Doubt",
    "title": "Don’t Speak",
    "duration": 256,
    "record_label": "Interscope Records"
  },
  {
    "genre": "Dance",
    "views": 21245,
    "artiste": "Lady Gaga",
    "title": "Bad Romance",
    "duration": 295,
    "record_label": "Interscope Records"
  },
  {
    "genre": "Pop Punk",
    "views": 22246,
    "artiste": "Green Day",
    "title": "American Idiot",
    "duration": 176,
    "record_label": "Reprise Records"
  },
  {
    "genre": "Reggaeton",
    "views": 23247,
    "artiste": "Luis Fonsi",
    "title": "Despacito",
    "duration": 229,
    "record_label": "Universal Music Latin"
  }
]
